pkg_platzi_final/__init__.py
pkg_platzi_final/main.py
pkg_platzi_final/hotel_management/__init__.py
pkg_platzi_final/hotel_management/customers.py
pkg_platzi_final/hotel_management/payments.py
pkg_platzi_final/hotel_management/reservations.py
pkg_platzi_final/hotel_management/rooms.py
pkg_platzi_final-0.4.0.dist-info/LICENSE.txt
pkg_platzi_final-0.4.0.dist-info/METADATA
pkg_platzi_final-0.4.0.dist-info/WHEEL
pkg_platzi_final-0.4.0.dist-info/top_level.txt
pkg_platzi_final-0.4.0.dist-info/RECORD
