Metadata-Version: 2.1
Name: pkg_platzi_final
Version: 0.4.0
Summary: Un sistema básico de gestión de reservas en Python
Home-page: https://github.com/Odelgadoo/pkg_platzi_final
Author: odelgado
Author-email: odelgadoo@gmail.com
License: UNKNOWN
Platform: UNKNOWN
Classifier: Programming Language :: Python :: 3
Classifier: License :: OSI Approved :: MIT License
Classifier: Operating System :: OS Independent
Requires-Python: >=3.10
License-File: LICENSE.txt
